Scweet/__init__.py
Scweet/__version__.py
Scweet/const.py
Scweet/mailtm.py
Scweet/scweet.py
Scweet/scweet_v1.8.py
Scweet/user.py
Scweet/utils.py
scweet-3.2.dist-info/licenses/LICENSE.txt
scweet-3.2.dist-info/METADATA
scweet-3.2.dist-info/WHEEL
scweet-3.2.dist-info/top_level.txt
scweet-3.2.dist-info/RECORD
