Metadata-Version: 2.4
Name: Scweet
Version: 3.2
Summary: Tool for scraping Tweets, User infos, Followers and Following
Home-page: https://github.com/Altimis/Scweet
Download-URL: https://github.com/Altimis/Scweet/archive/v3.0.tar.gz
Author: Yassine AIT JEDDI
Author-email: aitjeddiyassine@gmail.com
License: MIT
Keywords: twitter,scraper,python,crawl,following,followers,twitter-scraper,tweets
Classifier: Development Status :: 4 - Beta
Classifier: Intended Audience :: Developers
Classifier: Topic :: Software Development :: Build Tools
Classifier: License :: OSI Approved :: MIT License
Classifier: Programming Language :: Python :: 3.7
Classifier: Programming Language :: Python :: 3.8
Classifier: Programming Language :: Python :: 3.9
Classifier: Programming Language :: Python :: 3.10
Classifier: Programming Language :: Python :: 3.11
License-File: LICENSE.txt
Requires-Dist: certifi
Requires-Dist: python-dotenv
Requires-Dist: urllib3
Requires-Dist: PyVirtualDisplay
Requires-Dist: beautifulsoup4==4.12.3
Requires-Dist: nodriver==0.38.post1
Requires-Dist: requests
Dynamic: author
Dynamic: author-email
Dynamic: classifier
Dynamic: description
Dynamic: description-content-type
Dynamic: download-url
Dynamic: home-page
Dynamic: keywords
Dynamic: license
Dynamic: license-file
Dynamic: requires-dist
Dynamic: summary
